{"title":"Lecture Material","markdown":{"yaml":{"title":"Lecture Material","author":"Porobic Garate, Javier (Environment, Hobart)"},"headingText":"2022 Lectures (Summer School, Chile)","containsRefs":false,"markdown":"\n\n\nDay 1\n\n[Lecture_day01_P01_Atlantis_Chile.pdf](attachments/1751814444.pdf)\n\n[Lecture_day01_P02_Atlantis_Chile.pdf](attachments/1751814445.pdf)\n\n[Lecture_day01_P03_Atlantis_Chile.ppt](attachments/1751814446.ppt)\n\nDay 2\n\n[Lecture_day02_P01_Atlantis_Chile.pdf](attachments/1751814447.pdf)\n\n[Lecture_day02_P02 - Atlantis example.pptx](attachments/1751814448.pptx)\n\n[Lecture_day02_P03_modelling_decisions.pdf](attachments/1751814449.pdf)\n\nDay 3\n\n[Lecture_day03_P01_Atlantis_Chile.pdf](attachments/1751814450.pdf)\n\n[Lecture_day03_P02_Atlantis_Chile.pdf](attachments/1751814452.pdf)\n\n[Lecture_day03_P03_Atlantis_Tools.pdf](attachments/1751814453.pdf)\n\nDay 4\n\n[Lecture_day04_P01_Atlantis_Chile.pdf](attachments/1751814454.pdf)\n\n[Lecture_day04_P02_Atlantis_Chile.pdf](attachments/1751814455.pdf)\n\n#### 2021 Lectures\n\nVideos of the 2021 course are available from these links\n\nNotes on Lectures\n\n[Lecture 1 - Standard Atlantis overview](https://drive.google.com/file/d/1w4X1Ed-Q7pdRuuKeDvvZaJr3TMWlS-bR/view?usp=sharing)\n\n[Lecture 2 - SE Atlantis example](https://drive.google.com/file/d/1Y0sOkhDGHkm_y7ibJWKu4DuVTRY0x6-R/view?usp=sharing)\n\n[Lecture 3 - Installing code, working with SVN, compiling, running Atlantis (including using Docker)](https://drive.google.com/file/d/1kKJ9PAYqXyrWGGLkcJkBub9QBhRkrIFl/view?usp=sharing)\n\n[Lecture 4 - R tools](https://drive.google.com/file/d/1WNLK-p4n39DfRMpebz--PkB9Bdu-FJYq/view?usp=sharing)\n\n[Lecture 5 - Looking through code, diagnosing and troubleshooting common problems (best practice calibration)](https://drive.google.com/file/d/1ekrfM-g-z2LDEZ85wKa3UxfMGF9UP9wd/view?usp=sharing)\n\n[Lecture 6 - new functionality (multi-year migrations, fisheries and management links, coral reefs, ice, contaminants, physiology, invading species and land use)](https://drive.google.com/file/d/1rkZj_PldevkTYyuJkEkBw5f1KHYVuPOK/view?usp=sharing)\n\n#### 2008-2009 Lectures\n\n#### Theory and lecture heavy versions of teaching material that Beth used in 2008 and 2009\n\n[Lecture 1 - Intro Atlantis Modelling Concepts.ppt](attachments/43156533.ppt)   \n[Lecture 2 - Marine Ecology and Oceanography.ppt](attachments/43156524.ppt)   \n[Lecture 3 - Ecological Modelling.ppt](attachments/43156522.ppt)   \n[Lecture 4 - Resolution.ppt](attachments/43156520.ppt)   \n[Lecture 5 - Physics equations.ppt](attachments/43156531.ppt)   \n[Lecture 6 - Chemical equations.ppt](attachments/43156529.ppt)   \n[Lecture 7 - Primary Production.ppt](attachments/43156518.ppt)   \n[Lecture 8 - Biomass Pool Consumers.ppt](attachments/43156517.ppt)   \n[Lecture 9 - Vertebrates.ppt](attachments/43156516.ppt)   \n[Lecture 10 - Fisheries and Management.ppt](attachments/43156519.ppt)   \n[Lecture 11 - Socio-economics.ppt](attachments/43156525.ppt)   \n[Lecture 12 - Building Atlantis.ppt](attachments/43156506.ppt)   \n[Lecture 13 - Looking at Output.ppt](attachments/43156507.ppt)   \n[Lecture 14 - Running Atlantis.ppt](attachments/43156508.ppt)   \n[Lecture 15 - Main Loop.ppt](attachments/43156509.ppt)\n\n#### Seattle 2009 Teaching materials\n\nThe following is the teaching material that Isaac, Cam, and Peter used in Seattle, Sept 2009.  \nIncludes slides, handouts, and lab demos.  \nIncludes slides from Beth, Bec, Jason Link, Uwe Rosebrock, others:\n\n[AtlantisEcosysModelCourseSept2009.doc](attachments/43157076.doc)   \n[Day1_0930_Ecosystem Models (Cam).ppt](attachments/43157085.ppt)   \n[Day1_1115_KaplanIntroTo_Atlantis_Sept_2009.ppt](attachments/43157088.ppt)   \n[Day1_1330_Kaplan_SEAustralia_Atlantis_Sept82009.ppt](attachments/43157079.ppt)   \n[Day1_1430_Horne_Atlantis_California_8Sep2009.ppt](attachments/43157083.ppt)   \n[Day1_1500_KaplanDay1_ITQAcidification_Sept2009.ppt](attachments/43157080.ppt)   \n[Day1_1545_GOC case study (Cam).ppt](attachments/43157084.ppt)   \n[Day1_1700_handout.doc](attachments/43157072.doc)   \n[Day2_0915_Key modelling decisions (Cam).ppt](attachments/43157073.ppt)   \n[Day2_1045_KaplanFutureDevelopmentAtlantis2.ppt](attachments/43157074.ppt)   \n[Day2_1115_Atlantis Output.ppt](attachments/43157206.ppt)   \n[Day2_1145_Output visualization (Cam).ppt](attachments/43157078.ppt)   \n[Day2_1300_HandoutsPRM_CDF.doc](attachments/43157067.doc)   \n[Day2_1300_KaplanAtlantisInputFiles.ppt](attachments/43157203.ppt)   \n[Day2_1430_ECCALbioparams.xls](attachments/43157075.xls)   \n[Day3_0900_Handout_HowtoBuildanAtlantisModel_Feb18_2009.doc](attachments/43157086.doc)   \n[Day3_0930_ThoughtExperiments.doc](attachments/43157070.doc)   \n[Day3_1330_KaplanFitToHistory.ppt](attachments/43157091.ppt)   \n[Day3_1430_Ancillary tools (Cam).ppt](attachments/43157087.ppt)   \n[Day3_1630_KaplanCodeTour.ppt](attachments/43156514.ppt)   \n[ReadMe.txt](attachments/43157092.txt)   \n[Admin.zip](attachments/43157071.zip)   \nDay2_1115_PeterOutputDemo.zip - currently not in the archive, but contact Beth to chase up a copy or an equivalent  \n[Day2_1300_IsaacInputFiles.zip](attachments/43156515.zip)   \nDay3_1030_LabExercises.zip- currently not in the archive, but contact Beth to chase up a copy or an equivalent\n\n#### Hobart/Europe 2011 teaching powerpoints\n\nTeaching power points from Feb 2011 Workshop in Hobart. These are fairly short as its supposed to be more hands on.\n\n[LECTURE 1 - Atlantis2011.ppt](attachments/43157108.ppt)   \n[LECTURE 2 - Geometry 2011.ppt](attachments/43157105.ppt)   \n[LECTURE 3 - Physics 2011.ppt](attachments/43157106.ppt)   \n[LECTURE 4 - Biology 2011.ppt](attachments/43157107.ppt)   \n[LECTURE 5 - Fisheries_2011.ppt](attachments/43157109.ppt)   \n[LECTURE 6 - Running Atlantis.ppt](attachments/43157104.ppt)   \n[LECTURE 7 - Output Exploration.ppt](attachments/43157157.ppt)   \n[LECTURE 8 - Monitoring and assessments 2011.ppt](attachments/43157158.pptx)   \n[LECTURE 9 - Main loop and code 2011.ppt](attachments/43157103.ppt)\n\n[Introduction to Atlantis NetCDF](attachments/43156445.pptx)\n\n[Atlantis Code](attachments/43156444.pptx)\n","srcMarkdownNoYaml":"\n\n#### 2022 Lectures (Summer School, Chile)\n\nDay 1\n\n[Lecture_day01_P01_Atlantis_Chile.pdf](attachments/1751814444.pdf)\n\n[Lecture_day01_P02_Atlantis_Chile.pdf](attachments/1751814445.pdf)\n\n[Lecture_day01_P03_Atlantis_Chile.ppt](attachments/1751814446.ppt)\n\nDay 2\n\n[Lecture_day02_P01_Atlantis_Chile.pdf](attachments/1751814447.pdf)\n\n[Lecture_day02_P02 - Atlantis example.pptx](attachments/1751814448.pptx)\n\n[Lecture_day02_P03_modelling_decisions.pdf](attachments/1751814449.pdf)\n\nDay 3\n\n[Lecture_day03_P01_Atlantis_Chile.pdf](attachments/1751814450.pdf)\n\n[Lecture_day03_P02_Atlantis_Chile.pdf](attachments/1751814452.pdf)\n\n[Lecture_day03_P03_Atlantis_Tools.pdf](attachments/1751814453.pdf)\n\nDay 4\n\n[Lecture_day04_P01_Atlantis_Chile.pdf](attachments/1751814454.pdf)\n\n[Lecture_day04_P02_Atlantis_Chile.pdf](attachments/1751814455.pdf)\n\n#### 2021 Lectures\n\nVideos of the 2021 course are available from these links\n\nNotes on Lectures\n\n[Lecture 1 - Standard Atlantis overview](https://drive.google.com/file/d/1w4X1Ed-Q7pdRuuKeDvvZaJr3TMWlS-bR/view?usp=sharing)\n\n[Lecture 2 - SE Atlantis example](https://drive.google.com/file/d/1Y0sOkhDGHkm_y7ibJWKu4DuVTRY0x6-R/view?usp=sharing)\n\n[Lecture 3 - Installing code, working with SVN, compiling, running Atlantis (including using Docker)](https://drive.google.com/file/d/1kKJ9PAYqXyrWGGLkcJkBub9QBhRkrIFl/view?usp=sharing)\n\n[Lecture 4 - R tools](https://drive.google.com/file/d/1WNLK-p4n39DfRMpebz--PkB9Bdu-FJYq/view?usp=sharing)\n\n[Lecture 5 - Looking through code, diagnosing and troubleshooting common problems (best practice calibration)](https://drive.google.com/file/d/1ekrfM-g-z2LDEZ85wKa3UxfMGF9UP9wd/view?usp=sharing)\n\n[Lecture 6 - new functionality (multi-year migrations, fisheries and management links, coral reefs, ice, contaminants, physiology, invading species and land use)](https://drive.google.com/file/d/1rkZj_PldevkTYyuJkEkBw5f1KHYVuPOK/view?usp=sharing)\n\n#### 2008-2009 Lectures\n\n#### Theory and lecture heavy versions of teaching material that Beth used in 2008 and 2009\n\n[Lecture 1 - Intro Atlantis Modelling Concepts.ppt](attachments/43156533.ppt)   \n[Lecture 2 - Marine Ecology and Oceanography.ppt](attachments/43156524.ppt)   \n[Lecture 3 - Ecological Modelling.ppt](attachments/43156522.ppt)   \n[Lecture 4 - Resolution.ppt](attachments/43156520.ppt)   \n[Lecture 5 - Physics equations.ppt](attachments/43156531.ppt)   \n[Lecture 6 - Chemical equations.ppt](attachments/43156529.ppt)   \n[Lecture 7 - Primary Production.ppt](attachments/43156518.ppt)   \n[Lecture 8 - Biomass Pool Consumers.ppt](attachments/43156517.ppt)   \n[Lecture 9 - Vertebrates.ppt](attachments/43156516.ppt)   \n[Lecture 10 - Fisheries and Management.ppt](attachments/43156519.ppt)   \n[Lecture 11 - Socio-economics.ppt](attachments/43156525.ppt)   \n[Lecture 12 - Building Atlantis.ppt](attachments/43156506.ppt)   \n[Lecture 13 - Looking at Output.ppt](attachments/43156507.ppt)   \n[Lecture 14 - Running Atlantis.ppt](attachments/43156508.ppt)   \n[Lecture 15 - Main Loop.ppt](attachments/43156509.ppt)\n\n#### Seattle 2009 Teaching materials\n\nThe following is the teaching material that Isaac, Cam, and Peter used in Seattle, Sept 2009.  \nIncludes slides, handouts, and lab demos.  \nIncludes slides from Beth, Bec, Jason Link, Uwe Rosebrock, others:\n\n[AtlantisEcosysModelCourseSept2009.doc](attachments/43157076.doc)   \n[Day1_0930_Ecosystem Models (Cam).ppt](attachments/43157085.ppt)   \n[Day1_1115_KaplanIntroTo_Atlantis_Sept_2009.ppt](attachments/43157088.ppt)   \n[Day1_1330_Kaplan_SEAustralia_Atlantis_Sept82009.ppt](attachments/43157079.ppt)   \n[Day1_1430_Horne_Atlantis_California_8Sep2009.ppt](attachments/43157083.ppt)   \n[Day1_1500_KaplanDay1_ITQAcidification_Sept2009.ppt](attachments/43157080.ppt)   \n[Day1_1545_GOC case study (Cam).ppt](attachments/43157084.ppt)   \n[Day1_1700_handout.doc](attachments/43157072.doc)   \n[Day2_0915_Key modelling decisions (Cam).ppt](attachments/43157073.ppt)   \n[Day2_1045_KaplanFutureDevelopmentAtlantis2.ppt](attachments/43157074.ppt)   \n[Day2_1115_Atlantis Output.ppt](attachments/43157206.ppt)   \n[Day2_1145_Output visualization (Cam).ppt](attachments/43157078.ppt)   \n[Day2_1300_HandoutsPRM_CDF.doc](attachments/43157067.doc)   \n[Day2_1300_KaplanAtlantisInputFiles.ppt](attachments/43157203.ppt)   \n[Day2_1430_ECCALbioparams.xls](attachments/43157075.xls)   \n[Day3_0900_Handout_HowtoBuildanAtlantisModel_Feb18_2009.doc](attachments/43157086.doc)   \n[Day3_0930_ThoughtExperiments.doc](attachments/43157070.doc)   \n[Day3_1330_KaplanFitToHistory.ppt](attachments/43157091.ppt)   \n[Day3_1430_Ancillary tools (Cam).ppt](attachments/43157087.ppt)   \n[Day3_1630_KaplanCodeTour.ppt](attachments/43156514.ppt)   \n[ReadMe.txt](attachments/43157092.txt)   \n[Admin.zip](attachments/43157071.zip)   \nDay2_1115_PeterOutputDemo.zip - currently not in the archive, but contact Beth to chase up a copy or an equivalent  \n[Day2_1300_IsaacInputFiles.zip](attachments/43156515.zip)   \nDay3_1030_LabExercises.zip- currently not in the archive, but contact Beth to chase up a copy or an equivalent\n\n#### Hobart/Europe 2011 teaching powerpoints\n\nTeaching power points from Feb 2011 Workshop in Hobart. These are fairly short as its supposed to be more hands on.\n\n[LECTURE 1 - Atlantis2011.ppt](attachments/43157108.ppt)   \n[LECTURE 2 - Geometry 2011.ppt](attachments/43157105.ppt)   \n[LECTURE 3 - Physics 2011.ppt](attachments/43157106.ppt)   \n[LECTURE 4 - Biology 2011.ppt](attachments/43157107.ppt)   \n[LECTURE 5 - Fisheries_2011.ppt](attachments/43157109.ppt)   \n[LECTURE 6 - Running Atlantis.ppt](attachments/43157104.ppt)   \n[LECTURE 7 - Output Exploration.ppt](attachments/43157157.ppt)   \n[LECTURE 8 - Monitoring and assessments 2011.ppt](attachments/43157158.pptx)   \n[LECTURE 9 - Main loop and code 2011.ppt](attachments/43157103.ppt)\n\n[Introduction to Atlantis NetCDF](attachments/43156445.pptx)\n\n[Atlantis Code](attachments/43156444.pptx)\n"},"formats":{"html":{"identifier":{"display-name":"HTML","target-format":"html","base-format":"html"},"execute":{"fig-width":7,"fig-height":5,"fig-format":"retina","fig-dpi":96,"df-print":"default","error":false,"eval":true,"cache":null,"freeze":"auto","echo":true,"output":true,"warning":true,"include":true,"keep-md":false,"keep-ipynb":false,"ipynb":null,"enabled":null,"daemon":null,"daemon-restart":false,"debug":false,"ipynb-filters":[],"ipynb-shell-interactivity":null,"plotly-connected":true,"engine":"markdown"},"render":{"keep-tex":false,"keep-typ":false,"keep-source":false,"keep-hidden":false,"prefer-html":false,"output-divs":true,"output-ext":"html","fig-align":"default","fig-pos":null,"fig-env":null,"code-fold":"none","code-overflow":"wrap","code-link":false,"code-line-numbers":false,"code-tools":false,"tbl-colwidths":"auto","merge-includes":true,"inline-includes":false,"preserve-yaml":false,"latex-auto-mk":true,"latex-auto-install":true,"latex-clean":true,"latex-min-runs":1,"latex-max-runs":10,"latex-makeindex":"makeindex","latex-makeindex-opts":[],"latex-tlmgr-opts":[],"latex-input-paths":[],"latex-output-dir":null,"link-external-icon":false,"link-external-newwindow":false,"self-contained-math":false,"format-resources":[],"notebook-links":true},"pandoc":{"standalone":true,"wrap":"none","default-image-extension":"png","to":"html","css":["styles.css"],"toc":true,"toc-depth":3,"output-file":"lecture-material.html"},"language":{"toc-title-document":"Table of contents","toc-title-website":"On this page","related-formats-title":"Other Formats","related-notebooks-title":"Notebooks","source-notebooks-prefix":"Source","other-links-title":"Other Links","code-links-title":"Code Links","launch-dev-container-title":"Launch Dev Container","launch-binder-title":"Launch Binder","article-notebook-label":"Article Notebook","notebook-preview-download":"Download Notebook","notebook-preview-download-src":"Download Source","notebook-preview-back":"Back to Article","manuscript-meca-bundle":"MECA Bundle","section-title-abstract":"Abstract","section-title-appendices":"Appendices","section-title-footnotes":"Footnotes","section-title-references":"References","section-title-reuse":"Reuse","section-title-copyright":"Copyright","section-title-citation":"Citation","appendix-attribution-cite-as":"For attribution, please cite this work as:","appendix-attribution-bibtex":"BibTeX citation:","appendix-view-license":"View License","title-block-author-single":"Author","title-block-author-plural":"Authors","title-block-affiliation-single":"Affiliation","title-block-affiliation-plural":"Affiliations","title-block-published":"Published","title-block-modified":"Modified","title-block-keywords":"Keywords","callout-tip-title":"Tip","callout-note-title":"Note","callout-warning-title":"Warning","callout-important-title":"Important","callout-caution-title":"Caution","code-summary":"Code","code-tools-menu-caption":"Code","code-tools-show-all-code":"Show All Code","code-tools-hide-all-code":"Hide All Code","code-tools-view-source":"View Source","code-tools-source-code":"Source Code","tools-share":"Share","tools-download":"Download","code-line":"Line","code-lines":"Lines","copy-button-tooltip":"Copy to Clipboard","copy-button-tooltip-success":"Copied!","repo-action-links-edit":"Edit this page","repo-action-links-source":"View source","repo-action-links-issue":"Report an issue","back-to-top":"Back to top","search-no-results-text":"No results","search-matching-documents-text":"matching documents","search-copy-link-title":"Copy link to search","search-hide-matches-text":"Hide additional matches","search-more-match-text":"more match in this document","search-more-matches-text":"more matches in this document","search-clear-button-title":"Clear","search-text-placeholder":"","search-detached-cancel-button-title":"Cancel","search-submit-button-title":"Submit","search-label":"Search","toggle-section":"Toggle section","toggle-sidebar":"Toggle sidebar navigation","toggle-dark-mode":"Toggle dark mode","toggle-reader-mode":"Toggle reader mode","toggle-navigation":"Toggle navigation","crossref-fig-title":"Figure","crossref-tbl-title":"Table","crossref-lst-title":"Listing","crossref-thm-title":"Theorem","crossref-lem-title":"Lemma","crossref-cor-title":"Corollary","crossref-prp-title":"Proposition","crossref-cnj-title":"Conjecture","crossref-def-title":"Definition","crossref-exm-title":"Example","crossref-exr-title":"Exercise","crossref-ch-prefix":"Chapter","crossref-apx-prefix":"Appendix","crossref-sec-prefix":"Section","crossref-eq-prefix":"Equation","crossref-lof-title":"List of Figures","crossref-lot-title":"List of Tables","crossref-lol-title":"List of Listings","environment-proof-title":"Proof","environment-remark-title":"Remark","environment-solution-title":"Solution","listing-page-order-by":"Order By","listing-page-order-by-default":"Default","listing-page-order-by-date-asc":"Oldest","listing-page-order-by-date-desc":"Newest","listing-page-order-by-number-desc":"High to Low","listing-page-order-by-number-asc":"Low to High","listing-page-field-date":"Date","listing-page-field-title":"Title","listing-page-field-description":"Description","listing-page-field-author":"Author","listing-page-field-filename":"File Name","listing-page-field-filemodified":"Modified","listing-page-field-subtitle":"Subtitle","listing-page-field-readingtime":"Reading Time","listing-page-field-wordcount":"Word Count","listing-page-field-categories":"Categories","listing-page-minutes-compact":"{0} min","listing-page-category-all":"All","listing-page-no-matches":"No matching items","listing-page-words":"{0} words","listing-page-filter":"Filter","draft":"Draft"},"metadata":{"lang":"en","fig-responsive":true,"quarto-version":"1.8.26","theme":"cosmo","code-copy":true,"title":"Lecture Material","author":"Porobic Garate, Javier (Environment, Hobart)"},"extensions":{"book":{"multiFile":true}}}},"projectFormats":["html"]}