{"title":"Summit Participants","markdown":{"yaml":{"title":"Summit Participants","author":"Sinerchia, Matteo (Istituto per l'Ambiente Marino Costiero)"},"containsRefs":false,"markdown":"\n\nThis is the list of people who participated in the summit and their contact email.\n\n| Name | Institution | Email |\n| --- | --- | --- |\n| Aigo Takeshige | Atmosphere and Ocean Research Institute, The University of Tokyo | [a-takeshige@aori.u-tokyo.ac.jp](mailto:a-takeshige@aori.u-tokyo.ac.jp) |\n| Alexander Keth | Institute for Hydrobiology and Fisheries Science | [alexander.keth@uni-hamburg.de](mailto:alexander.keth@uni-hamburg.de) |\n| Ane Lopez De Gamiz | FUNDACION AZTI | [alopez@azti.es](mailto:alopez@azti.es) |\n| Asta Audzijonyte | University of Helsinki | [asta.audzijonyte@helsinki.fi](mailto:asta.audzijonyte@helsinki.fi) |\n| Bec Gorton | CSIRO | [bec.gorton@csiro.au](mailto:bec.gorton@csiro.au) |\n| Cameron Ainsworth | University of South Florida | [ainsworth@usf.edu](mailto:ainsworth@usf.edu) |\n| Cecilie Hansen | Institute of marine research | [cecilie.hansen@imr.no](mailto:cecilie.hansen@imr.no) |\n| Derek Tittensor | UNEP-WCMC - Invitational | [Derek.Tittensor@unep-wcmc.org](mailto:Derek.Tittensor@unep-wcmc.org) |\n| Eider Andonegi | FUNDACION AZTI | [eandonegi@azti.es](mailto:eandonegi@azti.es) |\n| Beth Fulton | CSIRO | [beth.fulton@csiro.au](mailto:beth.fulton@csiro.au) |\n| Emma Hodgson | University of Washington | [hodgsone@uw.edu](mailto:hodgsone@uw.edu) |\n| Erik Olsen | Havforskningsinstituttet | [eriko@imr.no](mailto:eriko@imr.no) |\n| Erla Sturludottir | University of Iceland | [erlasturl@gmail.com](mailto:erlasturl@gmail.com) |\n| Hector Lozano-Montes | CSIRO | [Hector.Lozano-Montes@csiro.au](mailto:Hector.Lozano-Montes@csiro.au) |\n| Hem Morzaria-Luna | CEDO Intercultural | [hemnalini.morzarialuna@noaa.gov](mailto:hemnalini.morzarialuna@noaa.gov) |\n| Hiroto Murase | National Research Institute of Far Seas Fisheries | [muraseh@affrc.go.jp](mailto:muraseh@affrc.go.jp) |\n| Holly Perryman | University of Miami - RSMAS | [hperryman@rsmas.miami.edu](mailto:hperryman@rsmas.miami.edu) |\n| Howard Townsend | NOAA Fisheries | [howard.townsend@noaa.gov](mailto:howard.townsend@noaa.gov) |\n| Isaac Kaplan | NOAA Fisheries Northwest Fisheries Science Center | [isaac.kaplan@noaa.gov](mailto:isaac.kaplan@noaa.gov) |\n| Jason Link | NOAA Fisheries | [jason.link@noaa.gov](mailto:jason.link@noaa.gov) |\n| Javier Porobic | University of Tasmania, CSIRO | [Javier.Porobic@utas.edu.au](mailto:Javier.Porobic@utas.edu.au) |\n| Jess Melbourne-Thomas | Australian Antarctic Division | [jess.melbourne-thomas@aad.gov.au](mailto:jess.melbourne-thomas@aad.gov.au) |\n| Joel Ortega Ortiz |  |  |\n| Kelli Johnson | University of Washington | [kfjohns@uw.edu](mailto:kfjohns@uw.edu) |\n| Kirsten Larsen | NOAA Fisheries | [kirsten.larsen@noaa.gov](mailto:kirsten.larsen@noaa.gov) |\n| Manuel Barange | Plymouth Marine Lab, UK | [MABA@pml.ac.uk](mailto:MABA@pml.ac.uk) |\n| Marie Savina | IFREMER | [msavinar@ifremer.fr](mailto:msavinar@ifremer.fr) |\n| Mariska Weijerman | JIMAR / NOAA Fisheries Pacific Islands Fisheries Science Center | [mariska.weijerman@noaa.gov](mailto:mariska.weijerman@noaa.gov) |\n| Matteo Sinerchia | CNR-IAMC | matteo.sinerchia@iamc.cnr.it |\n| Mette Skern-Mauritzen | Institute of Marine Research | [mettem@imr.no](mailto:mettem@imr.no) |\n| Michael Drexler | The Ocean Conservancy | [mdrexler@oceanconservancy.org](mailto:mdrexler@oceanconservancy.org) |\n| Robert Wildermuth | University of Massachusetts Dartmouth | [rwildermuth@umassd.edu](mailto:rwildermuth@umassd.edu) |\n| Robert Gamble | NOAA Fisheries Northeast Fisheries Science Center | [robert.gamble@noaa.gov](mailto:robert.gamble@noaa.gov) |\n| Russell (Rusty) Brainard | NOAA Fisheries Pacific Islands Fisheries Science Center | [rusty.brainard@noaa.gov](mailto:rusty.brainard@noaa.gov) |\n| Sarah Gaichas | NOAA Fisheries Northeast Fisheries Science Center | [sarah.gaichas@noaa.gov](mailto:sarah.gaichas@noaa.gov) |\n| Sean Lucey | NOAA Fisheries Northeast Fisheries Science Center | [sean.lucey@noaa.gov](mailto:sean.lucey@noaa.gov) |\n| Stephen Gosnell | Baruch College, City University of New York | [stephen.gosnell@baruch.cuny.edu](mailto:stephen.gosnell@baruch.cuny.edu) |\n| Takehiro Okuda | National Research Institute of Far Seas Fisheries, FRA | [okudy@affrc.go.jp](mailto:okudy@affrc.go.jp) |\n| Thibaut Houitte de la Chesnais | University of Tasmania, CSIRO | [thibaut.houittedelachesnais@utas.edu.au](mailto:thibaut.houittedelachesnais@utas.edu.au) |\n| Tom Ihde | ERT, Inc for NOAA Fisheries | [tom.ihde@noaa.gov](mailto:tom.ihde@noaa.gov) |\n| Trevor Hutton | CSIRO | [trevor.hutton@csiro.au](mailto:trevor.hutton@csiro.au) |\n| Vidette McGregor | NIWA | [vidette.mcgregor@niwa.co.nz](mailto:vidette.mcgregor@niwa.co.nz) |\n| Xinhua Zhu | Fisheries and Oceans canada | [xinhua.zhu@dfo-mpo.gc.ca](mailto:xinhua.zhu@dfo-mpo.gc.ca) |\n","srcMarkdownNoYaml":"\n\nThis is the list of people who participated in the summit and their contact email.\n\n| Name | Institution | Email |\n| --- | --- | --- |\n| Aigo Takeshige | Atmosphere and Ocean Research Institute, The University of Tokyo | [a-takeshige@aori.u-tokyo.ac.jp](mailto:a-takeshige@aori.u-tokyo.ac.jp) |\n| Alexander Keth | Institute for Hydrobiology and Fisheries Science | [alexander.keth@uni-hamburg.de](mailto:alexander.keth@uni-hamburg.de) |\n| Ane Lopez De Gamiz | FUNDACION AZTI | [alopez@azti.es](mailto:alopez@azti.es) |\n| Asta Audzijonyte | University of Helsinki | [asta.audzijonyte@helsinki.fi](mailto:asta.audzijonyte@helsinki.fi) |\n| Bec Gorton | CSIRO | [bec.gorton@csiro.au](mailto:bec.gorton@csiro.au) |\n| Cameron Ainsworth | University of South Florida | [ainsworth@usf.edu](mailto:ainsworth@usf.edu) |\n| Cecilie Hansen | Institute of marine research | [cecilie.hansen@imr.no](mailto:cecilie.hansen@imr.no) |\n| Derek Tittensor | UNEP-WCMC - Invitational | [Derek.Tittensor@unep-wcmc.org](mailto:Derek.Tittensor@unep-wcmc.org) |\n| Eider Andonegi | FUNDACION AZTI | [eandonegi@azti.es](mailto:eandonegi@azti.es) |\n| Beth Fulton | CSIRO | [beth.fulton@csiro.au](mailto:beth.fulton@csiro.au) |\n| Emma Hodgson | University of Washington | [hodgsone@uw.edu](mailto:hodgsone@uw.edu) |\n| Erik Olsen | Havforskningsinstituttet | [eriko@imr.no](mailto:eriko@imr.no) |\n| Erla Sturludottir | University of Iceland | [erlasturl@gmail.com](mailto:erlasturl@gmail.com) |\n| Hector Lozano-Montes | CSIRO | [Hector.Lozano-Montes@csiro.au](mailto:Hector.Lozano-Montes@csiro.au) |\n| Hem Morzaria-Luna | CEDO Intercultural | [hemnalini.morzarialuna@noaa.gov](mailto:hemnalini.morzarialuna@noaa.gov) |\n| Hiroto Murase | National Research Institute of Far Seas Fisheries | [muraseh@affrc.go.jp](mailto:muraseh@affrc.go.jp) |\n| Holly Perryman | University of Miami - RSMAS | [hperryman@rsmas.miami.edu](mailto:hperryman@rsmas.miami.edu) |\n| Howard Townsend | NOAA Fisheries | [howard.townsend@noaa.gov](mailto:howard.townsend@noaa.gov) |\n| Isaac Kaplan | NOAA Fisheries Northwest Fisheries Science Center | [isaac.kaplan@noaa.gov](mailto:isaac.kaplan@noaa.gov) |\n| Jason Link | NOAA Fisheries | [jason.link@noaa.gov](mailto:jason.link@noaa.gov) |\n| Javier Porobic | University of Tasmania, CSIRO | [Javier.Porobic@utas.edu.au](mailto:Javier.Porobic@utas.edu.au) |\n| Jess Melbourne-Thomas | Australian Antarctic Division | [jess.melbourne-thomas@aad.gov.au](mailto:jess.melbourne-thomas@aad.gov.au) |\n| Joel Ortega Ortiz |  |  |\n| Kelli Johnson | University of Washington | [kfjohns@uw.edu](mailto:kfjohns@uw.edu) |\n| Kirsten Larsen | NOAA Fisheries | [kirsten.larsen@noaa.gov](mailto:kirsten.larsen@noaa.gov) |\n| Manuel Barange | Plymouth Marine Lab, UK | [MABA@pml.ac.uk](mailto:MABA@pml.ac.uk) |\n| Marie Savina | IFREMER | [msavinar@ifremer.fr](mailto:msavinar@ifremer.fr) |\n| Mariska Weijerman | JIMAR / NOAA Fisheries Pacific Islands Fisheries Science Center | [mariska.weijerman@noaa.gov](mailto:mariska.weijerman@noaa.gov) |\n| Matteo Sinerchia | CNR-IAMC | matteo.sinerchia@iamc.cnr.it |\n| Mette Skern-Mauritzen | Institute of Marine Research | [mettem@imr.no](mailto:mettem@imr.no) |\n| Michael Drexler | The Ocean Conservancy | [mdrexler@oceanconservancy.org](mailto:mdrexler@oceanconservancy.org) |\n| Robert Wildermuth | University of Massachusetts Dartmouth | [rwildermuth@umassd.edu](mailto:rwildermuth@umassd.edu) |\n| Robert Gamble | NOAA Fisheries Northeast Fisheries Science Center | [robert.gamble@noaa.gov](mailto:robert.gamble@noaa.gov) |\n| Russell (Rusty) Brainard | NOAA Fisheries Pacific Islands Fisheries Science Center | [rusty.brainard@noaa.gov](mailto:rusty.brainard@noaa.gov) |\n| Sarah Gaichas | NOAA Fisheries Northeast Fisheries Science Center | [sarah.gaichas@noaa.gov](mailto:sarah.gaichas@noaa.gov) |\n| Sean Lucey | NOAA Fisheries Northeast Fisheries Science Center | [sean.lucey@noaa.gov](mailto:sean.lucey@noaa.gov) |\n| Stephen Gosnell | Baruch College, City University of New York | [stephen.gosnell@baruch.cuny.edu](mailto:stephen.gosnell@baruch.cuny.edu) |\n| Takehiro Okuda | National Research Institute of Far Seas Fisheries, FRA | [okudy@affrc.go.jp](mailto:okudy@affrc.go.jp) |\n| Thibaut Houitte de la Chesnais | University of Tasmania, CSIRO | [thibaut.houittedelachesnais@utas.edu.au](mailto:thibaut.houittedelachesnais@utas.edu.au) |\n| Tom Ihde | ERT, Inc for NOAA Fisheries | [tom.ihde@noaa.gov](mailto:tom.ihde@noaa.gov) |\n| Trevor Hutton | CSIRO | [trevor.hutton@csiro.au](mailto:trevor.hutton@csiro.au) |\n| Vidette McGregor | NIWA | [vidette.mcgregor@niwa.co.nz](mailto:vidette.mcgregor@niwa.co.nz) |\n| Xinhua Zhu | Fisheries and Oceans canada | [xinhua.zhu@dfo-mpo.gc.ca](mailto:xinhua.zhu@dfo-mpo.gc.ca) |\n"},"formats":{"html":{"identifier":{"display-name":"HTML","target-format":"html","base-format":"html"},"execute":{"fig-width":7,"fig-height":5,"fig-format":"retina","fig-dpi":96,"df-print":"default","error":false,"eval":true,"cache":null,"freeze":"auto","echo":true,"output":true,"warning":true,"include":true,"keep-md":false,"keep-ipynb":false,"ipynb":null,"enabled":null,"daemon":null,"daemon-restart":false,"debug":false,"ipynb-filters":[],"ipynb-shell-interactivity":null,"plotly-connected":true,"engine":"markdown"},"render":{"keep-tex":false,"keep-typ":false,"keep-source":false,"keep-hidden":false,"prefer-html":false,"output-divs":true,"output-ext":"html","fig-align":"default","fig-pos":null,"fig-env":null,"code-fold":"none","code-overflow":"wrap","code-link":false,"code-line-numbers":false,"code-tools":false,"tbl-colwidths":"auto","merge-includes":true,"inline-includes":false,"preserve-yaml":false,"latex-auto-mk":true,"latex-auto-install":true,"latex-clean":true,"latex-min-runs":1,"latex-max-runs":10,"latex-makeindex":"makeindex","latex-makeindex-opts":[],"latex-tlmgr-opts":[],"latex-input-paths":[],"latex-output-dir":null,"link-external-icon":false,"link-external-newwindow":false,"self-contained-math":false,"format-resources":[],"notebook-links":true},"pandoc":{"standalone":true,"wrap":"none","default-image-extension":"png","to":"html","css":["styles.css"],"toc":true,"toc-depth":3,"output-file":"summit-participants.html"},"language":{"toc-title-document":"Table of contents","toc-title-website":"On this page","related-formats-title":"Other Formats","related-notebooks-title":"Notebooks","source-notebooks-prefix":"Source","other-links-title":"Other Links","code-links-title":"Code Links","launch-dev-container-title":"Launch Dev Container","launch-binder-title":"Launch Binder","article-notebook-label":"Article Notebook","notebook-preview-download":"Download Notebook","notebook-preview-download-src":"Download Source","notebook-preview-back":"Back to Article","manuscript-meca-bundle":"MECA Bundle","section-title-abstract":"Abstract","section-title-appendices":"Appendices","section-title-footnotes":"Footnotes","section-title-references":"References","section-title-reuse":"Reuse","section-title-copyright":"Copyright","section-title-citation":"Citation","appendix-attribution-cite-as":"For attribution, please cite this work as:","appendix-attribution-bibtex":"BibTeX citation:","appendix-view-license":"View License","title-block-author-single":"Author","title-block-author-plural":"Authors","title-block-affiliation-single":"Affiliation","title-block-affiliation-plural":"Affiliations","title-block-published":"Published","title-block-modified":"Modified","title-block-keywords":"Keywords","callout-tip-title":"Tip","callout-note-title":"Note","callout-warning-title":"Warning","callout-important-title":"Important","callout-caution-title":"Caution","code-summary":"Code","code-tools-menu-caption":"Code","code-tools-show-all-code":"Show All Code","code-tools-hide-all-code":"Hide All Code","code-tools-view-source":"View Source","code-tools-source-code":"Source Code","tools-share":"Share","tools-download":"Download","code-line":"Line","code-lines":"Lines","copy-button-tooltip":"Copy to Clipboard","copy-button-tooltip-success":"Copied!","repo-action-links-edit":"Edit this page","repo-action-links-source":"View source","repo-action-links-issue":"Report an issue","back-to-top":"Back to top","search-no-results-text":"No results","search-matching-documents-text":"matching documents","search-copy-link-title":"Copy link to search","search-hide-matches-text":"Hide additional matches","search-more-match-text":"more match in this document","search-more-matches-text":"more matches in this document","search-clear-button-title":"Clear","search-text-placeholder":"","search-detached-cancel-button-title":"Cancel","search-submit-button-title":"Submit","search-label":"Search","toggle-section":"Toggle section","toggle-sidebar":"Toggle sidebar navigation","toggle-dark-mode":"Toggle dark mode","toggle-reader-mode":"Toggle reader mode","toggle-navigation":"Toggle navigation","crossref-fig-title":"Figure","crossref-tbl-title":"Table","crossref-lst-title":"Listing","crossref-thm-title":"Theorem","crossref-lem-title":"Lemma","crossref-cor-title":"Corollary","crossref-prp-title":"Proposition","crossref-cnj-title":"Conjecture","crossref-def-title":"Definition","crossref-exm-title":"Example","crossref-exr-title":"Exercise","crossref-ch-prefix":"Chapter","crossref-apx-prefix":"Appendix","crossref-sec-prefix":"Section","crossref-eq-prefix":"Equation","crossref-lof-title":"List of Figures","crossref-lot-title":"List of Tables","crossref-lol-title":"List of Listings","environment-proof-title":"Proof","environment-remark-title":"Remark","environment-solution-title":"Solution","listing-page-order-by":"Order By","listing-page-order-by-default":"Default","listing-page-order-by-date-asc":"Oldest","listing-page-order-by-date-desc":"Newest","listing-page-order-by-number-desc":"High to Low","listing-page-order-by-number-asc":"Low to High","listing-page-field-date":"Date","listing-page-field-title":"Title","listing-page-field-description":"Description","listing-page-field-author":"Author","listing-page-field-filename":"File Name","listing-page-field-filemodified":"Modified","listing-page-field-subtitle":"Subtitle","listing-page-field-readingtime":"Reading Time","listing-page-field-wordcount":"Word Count","listing-page-field-categories":"Categories","listing-page-minutes-compact":"{0} min","listing-page-category-all":"All","listing-page-no-matches":"No matching items","listing-page-words":"{0} words","listing-page-filter":"Filter","draft":"Draft"},"metadata":{"lang":"en","fig-responsive":true,"quarto-version":"1.8.26","theme":"cosmo","code-copy":true,"title":"Summit Participants","author":"Sinerchia, Matteo (Istituto per l'Ambiente Marino Costiero)"},"extensions":{"book":{"multiFile":true}}}},"projectFormats":["html"]}